MANIFEST.in
README.txt
collective.contentgenerator-configure.zcml
setup.cfg
setup.py
collective/__init__.py
collective.contentgenerator.egg-info/PKG-INFO
collective.contentgenerator.egg-info/SOURCES.txt
collective.contentgenerator.egg-info/dependency_links.txt
collective.contentgenerator.egg-info/entry_points.txt
collective.contentgenerator.egg-info/namespace_packages.txt
collective.contentgenerator.egg-info/not-zip-safe
collective.contentgenerator.egg-info/paster_plugins.txt
collective.contentgenerator.egg-info/requires.txt
collective.contentgenerator.egg-info/top_level.txt
collective/contentgenerator/ContentGenerator.py
collective/contentgenerator/UserGenerator.py
collective/contentgenerator/__init__.py
collective/contentgenerator/configure.zcml
collective/contentgenerator/profiles.zcml
collective/contentgenerator/setuphandlers.py
collective/contentgenerator/version.txt
collective/contentgenerator/profiles/default/collective.contentgenerator_various.txt
collective/contentgenerator/profiles/default/import_steps.xml
collective/contentgenerator/profiles/default/metadata.xml
collective/contentgenerator/profiles/intranet/collective.contentgenerator_various.txt
collective/contentgenerator/profiles/intranet/import_steps.xml
collective/contentgenerator/profiles/intranet/metadata.xml
collective/contentgenerator/profiles/public/collective.contentgenerator_various.txt
collective/contentgenerator/profiles/public/import_steps.xml
collective/contentgenerator/profiles/public/metadata.xml
collective/contentgenerator/tests/__init__.py
collective/contentgenerator/tests/base.py
collective/contentgenerator/tests/content.txt
collective/contentgenerator/tests/rss.txt
collective/contentgenerator/tests/test_content.py
collective/contentgenerator/tests/test_rss.py
collective/contentgenerator/tests/test_unit.py
collective/contentgenerator/tests/test_users.py
collective/contentgenerator/tests/unit.txt
collective/contentgenerator/tests/users.txt
docs/HISTORY.txt
docs/INSTALL.txt
docs/LICENSE.GPL
docs/LICENSE.txt
