Metadata-Version: 1.0
Name: collective.contentgenerator
Version: 0.2
Summary: Generates populated plone sites from specifed content profiles
Home-page: http://svn.plone.org/svn/collective/collective.contentgenerator
Author: Plone Collective
Author-email: internet-development@bristol.ac.uk
License: BSD
Keywords: web zope plone test content generation profile
Platform: UNKNOWN
Classifier: Programming Language :: Python
Classifier: Topic :: Software Development :: Libraries :: Python Modules
Classifier: Environment :: Web Environment
Classifier: Framework :: Plone
Classifier: Intended Audience :: Developers
Classifier: Intended Audience :: Other Audience
Classifier: Intended Audience :: System Administrators
Classifier: License :: OSI Approved :: BSD License
Classifier: Operating System :: OS Independent
Classifier: Development Status :: 4 - Beta
